setup.py
dsnd_probabilty_MAli/Binomialdistribution.py
dsnd_probabilty_MAli/Gaussiandistribution.py
dsnd_probabilty_MAli/Generaldistribution.py
dsnd_probabilty_MAli/__init__.py
dsnd_probabilty_MAli.egg-info/PKG-INFO
dsnd_probabilty_MAli.egg-info/SOURCES.txt
dsnd_probabilty_MAli.egg-info/dependency_links.txt
dsnd_probabilty_MAli.egg-info/not-zip-safe
dsnd_probabilty_MAli.egg-info/top_level.txt