Metadata-Version: 1.0
Name: dsnd-probabilty-MAli
Version: 1.0
Summary: Gaussian distributions
Home-page: UNKNOWN
Author: Mohammed M.Ali
Author-email: Mohamed.mamdouh2@gmail.com
License: UNKNOWN
Platform: UNKNOWN
